recreat/Configuration.py
recreat/LowLevelGenericFilters.c
recreat/LowLevelGenericFilters.dll
recreat/LowLevelGenericFilters.so
recreat/__init__.py
recreat/assessment.py
recreat/base.py
recreat/clustering.py
recreat/disaggregation.py
recreat/enumerations.py
recreat/exceptions.py
recreat/model.py
recreat/recreat_util.py
recreat/scalers.py
recreat/transformations.py
recreat-0.3.2.dist-info/licenses/LICENSE
recreat-0.3.2.dist-info/METADATA
recreat-0.3.2.dist-info/WHEEL
recreat-0.3.2.dist-info/entry_points.txt
recreat-0.3.2.dist-info/top_level.txt
recreat-0.3.2.dist-info/RECORD
