Metadata-Version: 2.4
Name: recreat
Version: 0.3.2
Summary: Indicators on Landscape Recreational Potential: Land use-based assessment of recreational opportunities from a multi-dimensional analytical lens
Author-email: Sebastian Scheuer <seb.scheuer@outlook.de>
License: Copyright (c) 2024 Sebastian Scheuer
Project-URL: Homepage, https://github.com/scheuerseb/recreat
Classifier: Development Status :: 3 - Alpha
Classifier: Intended Audience :: Science/Research
Classifier: Intended Audience :: Education
Classifier: Topic :: Scientific/Engineering :: GIS
Classifier: Topic :: Utilities
Classifier: Programming Language :: Python :: 3
Classifier: Programming Language :: C
Classifier: License :: OSI Approved :: MIT License
Classifier: Operating System :: Microsoft :: Windows
Classifier: Operating System :: POSIX :: Linux
Requires-Python: >=3.10
License-File: LICENSE
Requires-Dist: opencv-python
Requires-Dist: colorama
Requires-Dist: rich
Requires-Dist: rasterio
Requires-Dist: distancerasters
Requires-Dist: xarray-spatial
Requires-Dist: scipy
Requires-Dist: numpy
Requires-Dist: scikit-image
Requires-Dist: scikit-learn
Requires-Dist: pandas
Requires-Dist: typing
Requires-Dist: uuid
Requires-Dist: argparse
Requires-Dist: click
Dynamic: license-file
